synapse_wiki/__init__.py
synapse_wiki/api.py
synapse_wiki-0.0.1.dist-info/LICENSE
synapse_wiki-0.0.1.dist-info/METADATA
synapse_wiki-0.0.1.dist-info/WHEEL
synapse_wiki-0.0.1.dist-info/top_level.txt
synapse_wiki-0.0.1.dist-info/RECORD
