Metadata-Version: 2.1
Name: synapse-wiki
Version: 0.0.1
Summary: A python client for the Synapse API
Home-page: https://github.com/synapsewiki/synapse-python
Author: Synapse
Author-email: alex@synapse.wiki
License-File: LICENSE
Requires-Dist: requests
